{
  "objects": {
    "columnWidth": [
      {
        "properties": {
          "value": {
            "expr": {
              "Literal": {
                "Value": "184.3875696085222D"
              }
            }
          }
        },
        "selector": {
          "metadata": "capitulo.Título"
        }
      },
      {
        "properties": {
          "value": {
            "expr": {
              "Literal": {
                "Value": "53.961926581834064D"
              }
            }
          }
        },
        "selector": {
          "metadata": "MEDIDAS.Votos Totales"
        }
      },
      {
        "properties": {
          "value": {
            "expr": {
              "Literal": {
                "Value": "78.96485777888583D"
              }
            }
          }
        },
        "selector": {
          "metadata": "Sum(capitulo.Calificación Promedio)"
        }
      },
      {
        "properties": {
          "value": {
            "expr": {
              "Literal": {
                "Value": "118.85438640539195D"
              }
            }
          }
        },
        "selector": {
          "metadata": "tipo_capitulo.Tipo de Capitulo"
        }
      },
      {
        "properties": {
          "value": {
            "expr": {
              "Literal": {
                "Value": "41.75379781732879D"
              }
            }
          }
        },
        "selector": {
          "metadata": "Sum(capitulo.Número Capitulo)"
        }
      }
    ],
    "columnHeaders": [
      {
        "properties": {
          "fontColor": {
            "solid": {
              "color": {
                "expr": {
                  "ThemeDataColor": {
                    "ColorId": 0,
                    "Percent": 0
                  }
                }
              }
            }
          },
          "backColor": {
            "solid": {
              "color": {
                "expr": {
                  "Literal": {
                    "Value": "'#644D4A'"
                  }
                }
              }
            }
          },
          "alignment": {
            "expr": {
              "Literal": {
                "Value": "'Center'"
              }
            }
          },
          "fontSize": {
            "expr": {
              "Literal": {
                "Value": "8D"
              }
            }
          }
        }
      }
    ],
    "values": [
      {
        "properties": {
          "backColorPrimary": {
            "solid": {
              "color": {
                "expr": {
                  "Literal": {
                    "Value": "'#644D4A'"
                  }
                }
              }
            }
          },
          "backColorSecondary": {
            "solid": {
              "color": {
                "expr": {
                  "Literal": {
                    "Value": "'#975942'"
                  }
                }
              }
            }
          },
          "fontColorSecondary": {
            "solid": {
              "color": {
                "expr": {
                  "ThemeDataColor": {
                    "ColorId": 0,
                    "Percent": 0
                  }
                }
              }
            }
          },
          "fontColorPrimary": {
            "solid": {
              "color": {
                "expr": {
                  "ThemeDataColor": {
                    "ColorId": 0,
                    "Percent": 0
                  }
                }
              }
            }
          },
          "fontSize": {
            "expr": {
              "Literal": {
                "Value": "8D"
              }
            }
          }
        }
      },
      {
        "properties": {
          "backColor": {
            "solid": {
              "color": {
                "expr": {
                  "Conditional": {
                    "Cases": [
                      {
                        "Condition": {
                          "Comparison": {
                            "ComparisonKind": 0,
                            "Left": {
                              "Aggregation": {
                                "Expression": {
                                  "Column": {
                                    "Expression": {
                                      "SourceRef": {
                                        "Entity": "tipo_capitulo"
                                      }
                                    },
                                    "Property": "Tipo de Capitulo"
                                  }
                                },
                                "Function": 3
                              }
                            },
                            "Right": {
                              "Literal": {
                                "Value": "'Relleno'"
                              }
                            }
                          },
                          "Annotations": {
                            "PowerBI.SQExprEvaluationKind": 1,
                            "PowerBI.SQExprTextOperatorOption": 2
                          }
                        },
                        "Value": {
                          "Literal": {
                            "Value": "'#80403D'"
                          }
                        }
                      },
                      {
                        "Condition": {
                          "Comparison": {
                            "ComparisonKind": 0,
                            "Left": {
                              "Aggregation": {
                                "Expression": {
                                  "Column": {
                                    "Expression": {
                                      "SourceRef": {
                                        "Entity": "tipo_capitulo"
                                      }
                                    },
                                    "Property": "Tipo de Capitulo"
                                  }
                                },
                                "Function": 3
                              }
                            },
                            "Right": {
                              "Literal": {
                                "Value": "'Mixto (canon y relleno)'"
                              }
                            }
                          },
                          "Annotations": {
                            "PowerBI.SQExprEvaluationKind": 1,
                            "PowerBI.SQExprTextOperatorOption": 2
                          }
                        },
                        "Value": {
                          "Literal": {
                            "Value": "'#A89B29'"
                          }
                        }
                      },
                      {
                        "Condition": {
                          "Comparison": {
                            "ComparisonKind": 0,
                            "Left": {
                              "Aggregation": {
                                "Expression": {
                                  "Column": {
                                    "Expression": {
                                      "SourceRef": {
                                        "Entity": "tipo_capitulo"
                                      }
                                    },
                                    "Property": "Tipo de Capitulo"
                                  }
                                },
                                "Function": 3
                              }
                            },
                            "Right": {
                              "Literal": {
                                "Value": "'Canon del manga'"
                              }
                            }
                          },
                          "Annotations": {
                            "PowerBI.SQExprEvaluationKind": 1,
                            "PowerBI.SQExprTextOperatorOption": 2
                          }
                        },
                        "Value": {
                          "Literal": {
                            "Value": "'#5D6440'"
                          }
                        }
                      }
                    ]
                  }
                }
              }
            }
          },
          "fontColor": {
            "solid": {
              "color": {
                "expr": {
                  "Conditional": {
                    "Cases": [
                      {
                        "Condition": {
                          "Comparison": {
                            "ComparisonKind": 0,
                            "Left": {
                              "Aggregation": {
                                "Expression": {
                                  "Column": {
                                    "Expression": {
                                      "SourceRef": {
                                        "Entity": "tipo_capitulo"
                                      }
                                    },
                                    "Property": "Tipo de Capitulo"
                                  }
                                },
                                "Function": 3
                              }
                            },
                            "Right": {
                              "Literal": {
                                "Value": "'Relleno'"
                              }
                            }
                          },
                          "Annotations": {
                            "PowerBI.SQExprEvaluationKind": 1,
                            "PowerBI.SQExprTextOperatorOption": 2
                          }
                        },
                        "Value": {
                          "Literal": {
                            "Value": "'#FFFFFF'"
                          }
                        }
                      },
                      {
                        "Condition": {
                          "Comparison": {
                            "ComparisonKind": 0,
                            "Left": {
                              "Aggregation": {
                                "Expression": {
                                  "Column": {
                                    "Expression": {
                                      "SourceRef": {
                                        "Entity": "tipo_capitulo"
                                      }
                                    },
                                    "Property": "Tipo de Capitulo"
                                  }
                                },
                                "Function": 3
                              }
                            },
                            "Right": {
                              "Literal": {
                                "Value": "'Mixto (canon y relleno)'"
                              }
                            }
                          },
                          "Annotations": {
                            "PowerBI.SQExprEvaluationKind": 1,
                            "PowerBI.SQExprTextOperatorOption": 2
                          }
                        },
                        "Value": {
                          "Literal": {
                            "Value": "'#FFFFFF'"
                          }
                        }
                      },
                      {
                        "Condition": {
                          "Comparison": {
                            "ComparisonKind": 0,
                            "Left": {
                              "Aggregation": {
                                "Expression": {
                                  "Column": {
                                    "Expression": {
                                      "SourceRef": {
                                        "Entity": "tipo_capitulo"
                                      }
                                    },
                                    "Property": "Tipo de Capitulo"
                                  }
                                },
                                "Function": 3
                              }
                            },
                            "Right": {
                              "Literal": {
                                "Value": "'Canon del manga'"
                              }
                            }
                          },
                          "Annotations": {
                            "PowerBI.SQExprEvaluationKind": 1,
                            "PowerBI.SQExprTextOperatorOption": 2
                          }
                        },
                        "Value": {
                          "Literal": {
                            "Value": "'#FFFFFF'"
                          }
                        }
                      }
                    ]
                  }
                }
              }
            }
          }
        },
        "selector": {
          "data": [
            {
              "dataViewWildcard": {
                "matchingOption": 1
              }
            }
          ],
          "metadata": "tipo_capitulo.Tipo de Capitulo"
        }
      }
    ],
    "grid": [
      {
        "properties": {
          "gridHorizontal": {
            "expr": {
              "Literal": {
                "Value": "false"
              }
            }
          },
          "outlineColor": {
            "solid": {
              "color": {
                "expr": {
                  "ThemeDataColor": {
                    "ColorId": 4,
                    "Percent": 0.2
                  }
                }
              }
            }
          }
        }
      }
    ],
    "total": [
      {
        "properties": {
          "totals": {
            "expr": {
              "Literal": {
                "Value": "false"
              }
            }
          }
        }
      }
    ],
    "columnFormatting": [
      {
        "properties": {
          "alignment": {
            "expr": {
              "Literal": {
                "Value": "'Center'"
              }
            }
          }
        },
        "selector": {
          "metadata": "Sum(capitulo.Número Capitulo)"
        }
      },
      {
        "properties": {
          "alignment": {
            "expr": {
              "Literal": {
                "Value": "'Center'"
              }
            }
          }
        },
        "selector": {
          "metadata": "tipo_capitulo.Tipo de Capitulo"
        }
      },
      {
        "properties": {
          "alignment": {
            "expr": {
              "Literal": {
                "Value": "'Center'"
              }
            }
          }
        },
        "selector": {
          "metadata": "MEDIDAS.Votos Totales"
        }
      },
      {
        "properties": {
          "alignment": {
            "expr": {
              "Literal": {
                "Value": "'Center'"
              }
            }
          }
        },
        "selector": {
          "metadata": "Sum(capitulo.Calificación Promedio)"
        }
      }
    ]
  },
  "projectionOrdering": {
    "Values": [
      0,
      1,
      4,
      2,
      3
    ]
  },
  "queryMetadata": {
    "Select": [
      {
        "Restatement": "#",
        "Name": "Sum(capitulo.Número Capitulo)",
        "Type": 3,
        "Format": "0"
      },
      {
        "Restatement": "Capítulo",
        "Name": "capitulo.Título",
        "Type": 2048
      },
      {
        "Restatement": "Votos",
        "Name": "MEDIDAS.Votos Totales",
        "Type": 3,
        "Format": "0"
      },
      {
        "Restatement": "Calificación",
        "Name": "Sum(capitulo.Calificación Promedio)",
        "Type": 3,
        "Format": "0"
      },
      {
        "Restatement": "Tipo de Capítulo",
        "Name": "tipo_capitulo.Tipo de Capitulo",
        "Type": 2048
      }
    ]
  },
  "visualElements": [
    {
      "DataRoles": [
        {
          "Name": "Values",
          "Projection": 0,
          "isActive": false
        },
        {
          "Name": "Values",
          "Projection": 1,
          "isActive": false
        },
        {
          "Name": "Values",
          "Projection": 4,
          "isActive": false
        },
        {
          "Name": "Values",
          "Projection": 2,
          "isActive": false
        },
        {
          "Name": "Values",
          "Projection": 3,
          "isActive": false
        }
      ]
    }
  ],
  "selects": [
    {
      "displayName": "#",
      "format": "0",
      "queryName": "Sum(capitulo.Número Capitulo)",
      "roles": {
        "Values": true
      },
      "sort": 1,
      "sortOrder": 0,
      "type": {
        "category": null,
        "underlyingType": 260
      },
      "expr": {
        "Column": {
          "Expression": {
            "SourceRef": {
              "Entity": "capitulo"
            }
          },
          "Property": "Número Capitulo"
        }
      }
    },
    {
      "displayName": "Capítulo",
      "queryName": "capitulo.Título",
      "roles": {
        "Values": true
      },
      "type": {
        "category": null,
        "underlyingType": 1
      },
      "expr": {
        "Column": {
          "Expression": {
            "SourceRef": {
              "Entity": "capitulo"
            }
          },
          "Property": "Título"
        }
      }
    },
    {
      "displayName": "Votos",
      "format": "0",
      "queryName": "MEDIDAS.Votos Totales",
      "roles": {
        "Values": true
      },
      "type": {
        "category": null,
        "underlyingType": 260
      },
      "expr": {
        "Measure": {
          "Expression": {
            "SourceRef": {
              "Entity": "MEDIDAS"
            }
          },
          "Property": "Votos Totales"
        }
      }
    },
    {
      "displayName": "Calificación",
      "format": "0",
      "queryName": "Sum(capitulo.Calificación Promedio)",
      "roles": {
        "Values": true
      },
      "type": {
        "category": null,
        "underlyingType": 260
      },
      "expr": {
        "Column": {
          "Expression": {
            "SourceRef": {
              "Entity": "capitulo"
            }
          },
          "Property": "Calificación Promedio"
        }
      }
    },
    {
      "displayName": "Tipo de Capítulo",
      "queryName": "tipo_capitulo.Tipo de Capitulo",
      "roles": {
        "Values": true
      },
      "type": {
        "category": null,
        "underlyingType": 1
      },
      "expr": {
        "Column": {
          "Expression": {
            "SourceRef": {
              "Entity": "tipo_capitulo"
            }
          },
          "Property": "Tipo de Capitulo"
        }
      }
    },
    {
      "displayName": "Primera fecha: Tipo de Capitulo",
      "queryName": "Min(tipo_capitulo.Tipo de Capitulo)",
      "roles": {},
      "type": {
        "category": null,
        "underlyingType": 1
      },
      "expr": {
        "Aggregation": {
          "Expression": {
            "Column": {
              "Expression": {
                "SourceRef": {
                  "Entity": "tipo_capitulo"
                }
              },
              "Property": "Tipo de Capitulo"
            }
          },
          "Function": 3
        }
      },
      "relatedObjects": {
        "values": {
          "backColor": [
            {
              "data": [
                {
                  "dataViewWildcard": {
                    "matchingOption": 1
                  }
                }
              ],
              "metadata": "tipo_capitulo.Tipo de Capitulo"
            }
          ],
          "fontColor": [
            {
              "data": [
                {
                  "dataViewWildcard": {
                    "matchingOption": 1
                  }
                }
              ],
              "metadata": "tipo_capitulo.Tipo de Capitulo"
            }
          ]
        }
      }
    }
  ]
}